orcalib/__init__.py
orcalib/agents/__init__.py
orcalib/agents/action_add_memories.py
orcalib/agents/action_add_memories_test.py
orcalib/agents/action_prediction.py
orcalib/agents/action_prediction_test.py
orcalib/agents/agent_utils.py
orcalib/agents/agent_workflow.py
orcalib/agents/agent_workflow_test.py
orcalib/agents/bootstrap_classification_model.py
orcalib/agents/bootstrap_classification_model_test.py
orcalib/agents/describe_class_patterns.py
orcalib/agents/describe_class_patterns_test.py
orcalib/agents/describe_concept.py
orcalib/agents/explain_prediction.py
orcalib/agents/explain_prediction_test.py
orcalib/analysis/__init__.py
orcalib/analysis/analysis.py
orcalib/analysis/analysis_class_patterns.py
orcalib/analysis/analysis_class_patterns_test.py
orcalib/analysis/analysis_cluster.py
orcalib/analysis/analysis_cluster_test.py
orcalib/analysis/analysis_duplicate.py
orcalib/analysis/analysis_duplicate_test.py
orcalib/analysis/analysis_label.py
orcalib/analysis/analysis_label_test.py
orcalib/analysis/analysis_neighbor.py
orcalib/analysis/analysis_neighbor_test.py
orcalib/analysis/analysis_projection.py
orcalib/analysis/analysis_projection_test.py
orcalib/analysis/analysis_subconcept.py
orcalib/analysis/analysis_subconcept_test.py
orcalib/analysis/util.py
orcalib/analysis/util_test.py
orcalib/concepts/__init__.py
orcalib/concepts/concept_layer.py
orcalib/concepts/concept_layer_test.py
orcalib/concepts/recursive_concepts.py
orcalib/concepts/recursive_concepts_test.py
orcalib/conftest.py
orcalib/embedding/__init__.py
orcalib/embedding/embedding_evaluation.py
orcalib/embedding/embedding_evaluation_test.py
orcalib/embedding/embedding_finetuning.py
orcalib/embedding/embedding_finetuning_triplet_loss.py
orcalib/embedding/embedding_models.py
orcalib/embedding/embedding_models_test.py
orcalib/embedding/embedding_timeseries.py
orcalib/embedding/embedding_timeseries_test.py
orcalib/embedding/finetuning_proxy_loss.py
orcalib/memoryset/__init__.py
orcalib-0.0.98.dist-info/METADATA
orcalib-0.0.98.dist-info/WHEEL
orcalib-0.0.98.dist-info/RECORD
