Metadata-Version: 2.1
Name: orcalib
Version: 0.0.98
Summary: Orca Core Library
License: Apache-2.0
Author: Orca DB Inc.
Author-email: dev-rel@orcadb.ai
Requires-Python: >=3.12,<3.13
Classifier: License :: OSI Approved :: Apache Software License
Classifier: Programming Language :: Python :: 3
Classifier: Programming Language :: Python :: 3.12
Requires-Dist: datasets (>=3.1.0,<4.0.0)
Requires-Dist: einops (>=0.8.0,<0.9.0)
Requires-Dist: faiss-cpu (>=1.10.0,<2.0.0)
Requires-Dist: gcsfs (>=2024.9.0,<2025.0.0)
Requires-Dist: hdbscan (>=0.8.40,<0.9.0)
Requires-Dist: igraph (>=0.11.8,<0.12.0)
Requires-Dist: leidenalg (>=0.10.2,<0.11.0)
Requires-Dist: matplotlib (>=3.9.2,<4.0.0)
Requires-Dist: networkx (>=3.4.2,<4.0.0)
Requires-Dist: numpy (>=2.1.0,<3.0.0)
Requires-Dist: optuna (>=4.3.0,<5.0.0)
Requires-Dist: orjson (>=3.10.11,<4.0.0)
Requires-Dist: pillow (>=10.0.0,<11.0.0)
Requires-Dist: plotly (>=5.24.1,<6.0.0)
Requires-Dist: prettytable (>=3.12.0,<4.0.0)
Requires-Dist: pydantic-ai-slim[anthropic,openai] (>=0.4.10,<0.5.0)
Requires-Dist: pymilvus (==2.5.4)
Requires-Dist: s3fs (>=2024.9.0,<2025.0.0)
Requires-Dist: scikit-learn (>=1.5.2,<2.0.0)
Requires-Dist: sentence-transformers (==4.1.0)
Requires-Dist: torch (==2.5.1)
Requires-Dist: transformers[torch] (==4.52.4)
Requires-Dist: ts2vec (>=0.1,<0.2)
Requires-Dist: umap-learn (>=0.5.7,<0.6.0)
Requires-Dist: uuid-utils (>=0.10.0,<0.11.0)
